datetimerange/__init__.py
datetimerange/__version__.py
datetimerange/_core.py
datetimerange/py.typed
datetimerange-2.3.2.dist-info/licenses/LICENSE
datetimerange-2.3.2.dist-info/METADATA
datetimerange-2.3.2.dist-info/WHEEL
datetimerange-2.3.2.dist-info/top_level.txt
datetimerange-2.3.2.dist-info/RECORD
