Metadata-Version: 2.4
Name: DateTimeRange
Version: 2.3.2
Summary: DateTimeRange is a Python library to handle a time range. e.g. check whether a time is within the time range, get the intersection of time ranges, truncate a time range, iterate through a time range, and so forth.
Home-page: https://github.com/thombashi/DateTimeRange
Author: Tsuyoshi Hombashi
Author-email: tsuyoshi.hombashi@gmail.com
License: MIT License
Project-URL: Changelog, https://github.com/thombashi/DateTimeRange/blob/master/CHANGELOG.md
Project-URL: Documentation, https://datetimerange.rtfd.io/
Project-URL: Funding, https://github.com/sponsors/thombashi
Project-URL: Source, https://github.com/thombashi/DateTimeRange
Project-URL: Tracker, https://github.com/thombashi/DateTimeRange/issues
Keywords: datetimerange,datetime,time range
Classifier: Development Status :: 5 - Production/Stable
Classifier: Intended Audience :: Developers
Classifier: Intended Audience :: Information Technology
Classifier: License :: OSI Approved :: MIT License
Classifier: Operating System :: OS Independent
Classifier: Programming Language :: Python :: 3
Classifier: Programming Language :: Python :: 3.9
Classifier: Programming Language :: Python :: 3.10
Classifier: Programming Language :: Python :: 3.11
Classifier: Programming Language :: Python :: 3.12
Classifier: Programming Language :: Python :: 3.13
Classifier: Programming Language :: Python :: 3 :: Only
Classifier: Topic :: Software Development :: Libraries
Classifier: Topic :: Software Development :: Libraries :: Python Modules
Classifier: Topic :: Text Processing
Classifier: Typing :: Typed
Requires-Python: >=3.9
License-File: LICENSE
Requires-Dist: python-dateutil<3,>=2.4.2
Requires-Dist: typepy[datetime]<2,>=1.3.2
Provides-Extra: docs
Requires-Dist: path>=13; extra == "docs"
Requires-Dist: readmemaker>=1.1.0; extra == "docs"
Requires-Dist: sphinx_rtd_theme>=1.2.2; extra == "docs"
Requires-Dist: Sphinx>=2.4; extra == "docs"
Provides-Extra: test
Requires-Dist: pytest>=6.0.1; extra == "test"
Requires-Dist: pytest-md-report>=0.6.2; extra == "test"
Requires-Dist: pytz; extra == "test"
Dynamic: author
Dynamic: author-email
Dynamic: classifier
Dynamic: description
Dynamic: description-content-type
Dynamic: home-page
Dynamic: keywords
Dynamic: license
Dynamic: license-file
Dynamic: project-url
Dynamic: provides-extra
Dynamic: requires-dist
Dynamic: requires-python
Dynamic: summary
